FullSpeedPython/README.md
FullSpeedPython/__init__.py
FullSpeedPython/__main__.py
FullSpeedPython/file.epub
FullSpeedPython/index.html
FullSpeedPython/css/__init__.py
FullSpeedPython/css/annotations.css
FullSpeedPython/css/main.css
FullSpeedPython/css/normalize.css
FullSpeedPython/css/popup.css
FullSpeedPython/font/__init__.py
FullSpeedPython/font/fontello.eot
FullSpeedPython/font/fontello.svg
FullSpeedPython/font/fontello.ttf
FullSpeedPython/font/fontello.woff
FullSpeedPython/img/__init__.py
FullSpeedPython/img/annotator-glyph-sprite.png
FullSpeedPython/img/annotator-icon-sprite.png
FullSpeedPython/img/apple-touch-icon.png
FullSpeedPython/img/cancelfullscreen.png
FullSpeedPython/img/close.png
FullSpeedPython/img/fullscreen.png
FullSpeedPython/img/loader.gif
FullSpeedPython/img/menu-icon.png
FullSpeedPython/img/save.png
FullSpeedPython/img/saved.png
FullSpeedPython/img/settings-s.png
FullSpeedPython/img/settings.png
FullSpeedPython/img/star.png
FullSpeedPython/js/__init__.py
FullSpeedPython/js/epub.js
FullSpeedPython/js/epub.min.js
FullSpeedPython/js/epub.min.map
FullSpeedPython/js/hooks.min.js
FullSpeedPython/js/hooks.min.map
FullSpeedPython/js/reader.js
FullSpeedPython/js/reader.js.map
FullSpeedPython/js/reader.min.js
FullSpeedPython/js/reader.min.map
FullSpeedPython/js/hooks/__init__.py
FullSpeedPython/js/hooks/extensions/__init__.py
FullSpeedPython/js/hooks/extensions/highlight.js
FullSpeedPython/js/libs/__init__.py
FullSpeedPython/js/libs/jquery.min.js
FullSpeedPython/js/libs/localforage.min.js
FullSpeedPython/js/libs/screenfull.js
FullSpeedPython/js/libs/screenfull.min.js
FullSpeedPython/js/libs/zip.min.js
FullSpeedPython/js/plugins/__init__.py
FullSpeedPython/js/plugins/hypothesis.js
FullSpeedPython/js/plugins/search.js
full_speed_python-2024.3.3.0.dist-info/METADATA
full_speed_python-2024.3.3.0.dist-info/WHEEL
full_speed_python-2024.3.3.0.dist-info/entry_points.txt
full_speed_python-2024.3.3.0.dist-info/top_level.txt
full_speed_python-2024.3.3.0.dist-info/RECORD
